{
  "metadata": {
    "location": "Upper Station Weir",
    "species": "Sockeye",
    "year": 1931,
    "data_type": "historical_escapement",
    "source": "Historical weir operations",
    "notes": "Transition to scientific monitoring",
    "total_count": 15416,
    "data_points": 27
  },
  "DATA": [
    [
      "2024-06-15",
      "Upper Station Weir",
      "271",
      "Daily count - Transition to scientific monitoring"
    ],
    [
      "2024-06-16",
      "Upper Station Weir",
      "341",
      "Daily count - Transition to scientific monitoring"
    ],
    [
      "2024-06-17",
      "Upper Station Weir",
      "275",
      "Daily count - Transition to scientific monitoring"
    ],
    [
      "2024-06-18",
      "Upper Station Weir",
      "305",
      "Daily count - Transition to scientific monitoring"
    ],
    [
      "2024-06-19",
      "Upper Station Weir",
      "343",
      "Daily count - Transition to scientific monitoring"
    ],
    [
      "2024-06-20",
      "Upper Station Weir",
      "265",
      "Daily count - Transition to scientific monitoring"
    ],
    [
      "2024-06-21",
      "Upper Station Weir",
      "272",
      "Daily count - Transition to scientific monitoring"
    ],
    [
      "2024-06-22",
      "Upper Station Weir",
      "275",
      "Daily count - Transition to scientific monitoring"
    ],
    [
      "2024-06-23",
      "Upper Station Weir",
      "274",
      "Daily count - Transition to scientific monitoring"
    ],
    [
      "2024-06-24",
      "Upper Station Weir",
      "310",
      "Daily count - Transition to scientific monitoring"
    ],
    [
      "2024-06-25",
      "Upper Station Weir",
      "312",
      "Daily count - Transition to scientific monitoring"
    ],
    [
      "2024-06-26",
      "Upper Station Weir",
      "270",
      "Daily count - Transition to scientific monitoring"
    ],
    [
      "2024-06-27",
      "Upper Station Weir",
      "294",
      "Daily count - Transition to scientific monitoring"
    ],
    [
      "2024-06-28",
      "Upper Station Weir",
      "302",
      "Daily count - Transition to scientific monitoring"
    ],
    [
      "2024-06-29",
      "Upper Station Weir",
      "275",
      "Daily count - Transition to scientific monitoring"
    ],
    [
      "2024-06-30",
      "Upper Station Weir",
      "287",
      "Daily count - Transition to scientific monitoring"
    ],
    [
      "2024-07-01",
      "Upper Station Weir",
      "333",
      "Daily count - Transition to scientific monitoring"
    ],
    [
      "2024-07-02",
      "Upper Station Weir",
      "313",
      "Daily count - Transition to scientific monitoring"
    ],
    [
      "2024-07-03",
      "Upper Station Weir",
      "731",
      "Daily count - Transition to scientific monitoring"
    ],
    [
      "2024-07-04",
      "Upper Station Weir",
      "754",
      "Daily count - Transition to scientific monitoring"
    ],
    [
      "2024-07-05",
      "Upper Station Weir",
      "840",
      "Daily count - Transition to scientific monitoring"
    ],
    [
      "2024-07-06",
      "Upper Station Weir",
      "740",
      "Daily count - Transition to scientific monitoring"
    ],
    [
      "2024-07-07",
      "Upper Station Weir",
      "1407",
      "Daily count - Transition to scientific monitoring"
    ],
    [
      "2024-07-08",
      "Upper Station Weir",
      "1671",
      "Daily count - Transition to scientific monitoring"
    ],
    [
      "2024-07-09",
      "Upper Station Weir",
      "1666",
      "Daily count - Transition to scientific monitoring"
    ],
    [
      "2024-07-10",
      "Upper Station Weir",
      "2277",
      "Daily count - Transition to scientific monitoring"
    ],
    [
      "2024-07-11",
      "Upper Station Weir",
      "1509",
      "Daily count - Transition to scientific monitoring"
    ]
  ]
}